{
	"info": {
		"_postman_id": "69598bbb-2ef3-4c59-bc21-2165c15ff545",
		"name": "CHAT_APP",
		"schema": "https://schema.getpostman.com/json/collection/v2.1.0/collection.json",
		"_exporter_id": "32147624",
		"_collection_link": "https://gold-satellite-31461.postman.co/workspace/My-Workspace~dd720be5-1953-4914-8461-8b89d3298a25/collection/32147624-69598bbb-2ef3-4c59-bc21-2165c15ff545?action=share&source=collection_link&creator=32147624"
	},
	"item": [
		{
			"name": "AUTH",
			"item": [
				{
					"name": "SIGNUP",
					"request": {
						"method": "POST",
						"header": [],
						"body": {
							"mode": "raw",
							"raw": "{\n    \"fullName\" : \"alex\",\n    \"username\" : \"alex\",\n    \"password\" : \"Test@123\",\n    \"confirmPassword\" : \"Test@123\",\n    \"gender\" : \"male\"\n}",
							"options": {
								"raw": {
									"language": "json"
								}
							}
						},
						"url": {
							"raw": "http://localhost:5000/api/auth/signup",
							"protocol": "http",
							"host": [
								"localhost"
							],
							"port": "5000",
							"path": [
								"api",
								"auth",
								"signup"
							]
						}
					},
					"response": []
				},
				{
					"name": "LOGIN",
					"request": {
						"method": "POST",
						"header": [],
						"body": {
							"mode": "raw",
							"raw": "{\n    \"username\": \"alex\",\n    \"password\": \"Test@123\"\n}",
							"options": {
								"raw": {
									"language": "json"
								}
							}
						},
						"url": {
							"raw": "http://localhost:5000/api/auth/login",
							"protocol": "http",
							"host": [
								"localhost"
							],
							"port": "5000",
							"path": [
								"api",
								"auth",
								"login"
							]
						}
					},
					"response": []
				},
				{
					"name": "GETME",
					"protocolProfileBehavior": {
						"disableBodyPruning": true
					},
					"request": {
						"method": "GET",
						"header": [],
						"body": {
							"mode": "formdata",
							"formdata": []
						},
						"url": {
							"raw": "http://localhost:5000/api/auth/getme",
							"protocol": "http",
							"host": [
								"localhost"
							],
							"port": "5000",
							"path": [
								"api",
								"auth",
								"getme"
							]
						}
					},
					"response": []
				},
				{
					"name": "LOGOUT",
					"request": {
						"method": "POST",
						"header": [],
						"url": {
							"raw": "http://localhost:5000/api/auth/logout",
							"protocol": "http",
							"host": [
								"localhost"
							],
							"port": "5000",
							"path": [
								"api",
								"auth",
								"logout"
							]
						}
					},
					"response": []
				}
			]
		},
		{
			"name": "MESSAGES",
			"item": [
				{
					"name": "SENDMESSAGE",
					"request": {
						"method": "POST",
						"header": [],
						"body": {
							"mode": "raw",
							"raw": "{\n    \"message\": \"third mesage \"\n}",
							"options": {
								"raw": {
									"language": "json"
								}
							}
						},
						"url": {
							"raw": "http://localhost:5000/api/messages/send/clz4ha7od000064ovvsrzc7j9",
							"protocol": "http",
							"host": [
								"localhost"
							],
							"port": "5000",
							"path": [
								"api",
								"messages",
								"send",
								"clz4ha7od000064ovvsrzc7j9"
							]
						}
					},
					"response": []
				},
				{
					"name": "GETMESSAGE",
					"request": {
						"method": "GET",
						"header": [],
						"url": {
							"raw": "http://localhost:5000/api/messages/clz4ha7od000064ovvsrzc7j9",
							"protocol": "http",
							"host": [
								"localhost"
							],
							"port": "5000",
							"path": [
								"api",
								"messages",
								"clz4ha7od000064ovvsrzc7j9"
							]
						}
					},
					"response": []
				},
				{
					"name": "GETUSERS-SIDEBAR",
					"request": {
						"method": "GET",
						"header": [],
						"url": {
							"raw": "http://localhost:5000/api/messages/getconversations",
							"protocol": "http",
							"host": [
								"localhost"
							],
							"port": "5000",
							"path": [
								"api",
								"messages",
								"getconversations"
							]
						}
					},
					"response": []
				}
			]
		}
	]
}